py_dactyl-2.1.2.dist-info/licenses/LICENSE
pydactyl/__init__.py
pydactyl/api_client.py
pydactyl/async_api_client.py
pydactyl/constants.py
pydactyl/exceptions.py
pydactyl/responses.py
pydactyl/api/__init__.py
pydactyl/api/async_base.py
pydactyl/api/base.py
pydactyl/api/locations.py
pydactyl/api/nests.py
pydactyl/api/nodes.py
pydactyl/api/servers.py
pydactyl/api/user.py
pydactyl/api/application/__init__.py
pydactyl/api/application/async_locations.py
pydactyl/api/application/async_nests.py
pydactyl/api/application/async_nodes.py
pydactyl/api/application/async_servers.py
pydactyl/api/application/async_user.py
pydactyl/api/client/__init__.py
pydactyl/api/client/async_client_api.py
pydactyl/api/client/client_api.py
pydactyl/api/client/account/__init__.py
pydactyl/api/client/account/async_base.py
pydactyl/api/client/account/base.py
pydactyl/api/client/servers/__init__.py
pydactyl/api/client/servers/async_backups.py
pydactyl/api/client/servers/async_base.py
pydactyl/api/client/servers/async_databases.py
pydactyl/api/client/servers/async_files.py
pydactyl/api/client/servers/async_network.py
pydactyl/api/client/servers/async_schedules.py
pydactyl/api/client/servers/async_settings.py
pydactyl/api/client/servers/async_startup.py
pydactyl/api/client/servers/async_users.py
pydactyl/api/client/servers/async_websocket_client.py
pydactyl/api/client/servers/backups.py
pydactyl/api/client/servers/base.py
pydactyl/api/client/servers/databases.py
pydactyl/api/client/servers/files.py
pydactyl/api/client/servers/network.py
pydactyl/api/client/servers/schedules.py
pydactyl/api/client/servers/settings.py
pydactyl/api/client/servers/startup.py
pydactyl/api/client/servers/users.py
pydactyl/api/client/servers/websocket_client.py
tests/__init__.py
tests/application/__init__.py
tests/application/async/__init__.py
tests/application/async/nests_test.py
tests/application/async/nodes_test.py
tests/application/async/servers_test.py
tests/application/async/user_test.py
tests/application/sync/__init__.py
py_dactyl-2.1.2.dist-info/METADATA
py_dactyl-2.1.2.dist-info/WHEEL
py_dactyl-2.1.2.dist-info/top_level.txt
py_dactyl-2.1.2.dist-info/RECORD
