Metadata-Version: 2.4
Name: py-dactyl
Version: 2.1.2
Summary: An easy to use Python wrapper for the Pterodactyl Panel API.
Home-page: https://github.com/iamkubi/pydactyl
Author: Ryan Kubiak
Author-email: iamkubi@gmail.com
Project-URL: Documentation, https://pydactyl.readthedocs.io/
Project-URL: Source, https://github.com/iamkubi/pydactyl
Classifier: Programming Language :: Python :: 3
Classifier: License :: OSI Approved :: MIT License
Classifier: Natural Language :: English
Classifier: Operating System :: OS Independent
Requires-Python: >=3.4
License-File: LICENSE
Requires-Dist: aiohttp
Requires-Dist: requests>=2.21.0
Requires-Dist: websocket-client
Dynamic: author
Dynamic: author-email
Dynamic: classifier
Dynamic: description
Dynamic: description-content-type
Dynamic: home-page
Dynamic: license-file
Dynamic: project-url
Dynamic: requires-dist
Dynamic: requires-python
Dynamic: summary
